omnidb/__init__.py
omnidb/app.py
omnidb/dialects.py
omnidb/dbapi/__init__.py
omnidb/dbapi/connection.py
omnidb/dbapi/cursor.py
omnidb/dbapi/decorators.py
omnidb/dbapi/exceptions.py
omnidb/dbapi/types.py
omnidb-0.1.0.dist-info/METADATA
omnidb-0.1.0.dist-info/WHEEL
omnidb-0.1.0.dist-info/entry_points.txt
omnidb-0.1.0.dist-info/top_level.txt
omnidb-0.1.0.dist-info/RECORD
