Metadata-Version: 2.1
Name: omnidb
Version: 0.1.0
Summary: A database for testing different SQL dialects
Requires-Python: >=3.11
Requires-Dist: aiosqlite>=0.20.0
Requires-Dist: click>=8.1.7
Requires-Dist: pydantic>=2.10.3
Requires-Dist: quart-schema>=0.20.0
Requires-Dist: quart>=0.19.9
Requires-Dist: requests>=2.32.3
Requires-Dist: ruff>=0.8.1
Requires-Dist: sqlalchemy>=2.0.36
Requires-Dist: sqlglot>=25.33.0
Requires-Dist: uvicorn>=0.32.1
Requires-Dist: yarl>=1.18.3
